django_hierarchical_models/__init__.py
django_hierarchical_models/models/__init__.py
django_hierarchical_models/models/exceptions.py
django_hierarchical_models/models/hierarchical_model.py
django_hierarchical_models/models/node.py
django_hierarchical_models-2.1.0.dist-info/LICENSE
django_hierarchical_models-2.1.0.dist-info/METADATA
django_hierarchical_models-2.1.0.dist-info/WHEEL
django_hierarchical_models-2.1.0.dist-info/RECORD
