Metadata-Version: 2.1
Name: django-hierarchical-models
Version: 2.1.0
Summary: Adds hierarchical models to Django
Home-page: https://github.com/rcxwhiz/django-hierarchical-models
License: MIT
Author: Josh Bedwell
Author-email: rcxwhiz@gmail.com
Requires-Python: >=3.10,<4.0
Classifier: Framework :: Django
Classifier: Framework :: Django :: 4.2
Classifier: Framework :: Django :: 5.0
Classifier: License :: OSI Approved :: MIT License
Classifier: Programming Language :: Python :: 3
Classifier: Programming Language :: Python :: 3.10
Classifier: Programming Language :: Python :: 3.11
Classifier: Programming Language :: Python :: 3.12
Requires-Dist: django (>=4.2,<6.0)
Project-URL: Repository, https://github.com/rcxwhiz/django-hierarchical-models
